EdgePrediction/EdgePrediction.py
EdgePrediction/Objective.py
EdgePrediction/__init__.py
EdgePrediction/errors.py
EdgePrediction/utils/NumpyEncoder.py
EdgePrediction/utils/__init__.py
EdgePrediction/utils/merge_files.py
edgeprediction-0.2.1.4.dist-info/LICENSE
edgeprediction-0.2.1.4.dist-info/METADATA
edgeprediction-0.2.1.4.dist-info/WHEEL
edgeprediction-0.2.1.4.dist-info/top_level.txt
edgeprediction-0.2.1.4.dist-info/RECORD
