Metadata-Version: 2.1
Name: edgeprediction
Version: 0.2.1.4
Summary: Predict missing edges in a knowledge graph
Home-page: https://github.com/KHP-Informatics/ADR-graph
Author: Dan Bean
Author-email: daniel.bean@kcl.ac.uk
License: UNKNOWN
Platform: UNKNOWN
Classifier: Programming Language :: Python :: 3
Classifier: License :: OSI Approved :: GNU Lesser General Public License v3 (LGPLv3)
Classifier: Operating System :: OS Independent
Requires-Python: >=3.6
Requires-Dist: numpy (~=1.20.0)
Requires-Dist: python-igraph (~=0.8.3)
Requires-Dist: rpy2 (==3.4.2)
Requires-Dist: scipy (~=1.6.0)
Requires-Dist: db-edges (==0.0.3)
Requires-Dist: pandas (~=1.2.1)
